exo_changelog/__init__.py
exo_changelog/apps.py
exo_changelog/autodetector.py
exo_changelog/change.py
exo_changelog/exceptions.py
exo_changelog/executor.py
exo_changelog/graph.py
exo_changelog/loader.py
exo_changelog/models.py
exo_changelog/operations.py
exo_changelog/recorder.py
exo_changelog/urls.py
exo_changelog/views.py
exo_changelog/writer.py
exo_changelog/management/__init__.py
exo_changelog/management/commands/__init__.py
exo_changelog/management/commands/applychange.py
exo_changelog/management/commands/makechange.py
exo_changelog/migrations/0001_initial.py
exo_changelog/migrations/__init__.py
exo_changelog/static/css/exo_changelog.css
exo_changelog/static/js/exo_changelog.js
exo_changelog/templates/exo_changelog/base.html
exo_changelog-0.1.7.dist-info/AUTHORS.rst
exo_changelog-0.1.7.dist-info/LICENSE
exo_changelog-0.1.7.dist-info/METADATA
exo_changelog-0.1.7.dist-info/WHEEL
exo_changelog-0.1.7.dist-info/top_level.txt
exo_changelog-0.1.7.dist-info/RECORD
