Metadata-Version: 2.1
Name: exo-changelog
Version: 0.1.7
Summary: Manage changelog as migrations
Home-page: https://github.com/exolever/django-changelog
Author: Tomas Garzon
Author-email: tomasgarzonhervas@gmail.com
License: BSD
Keywords: exo-changelog
Platform: UNKNOWN
Classifier: Development Status :: 3 - Alpha
Classifier: Framework :: Django :: 1.11
Classifier: Intended Audience :: Developers
Classifier: License :: OSI Approved :: BSD License
Classifier: Natural Language :: English
Classifier: Programming Language :: Python :: 2
Classifier: Programming Language :: Python :: 2.7
Classifier: Programming Language :: Python :: 3
Classifier: Programming Language :: Python :: 3.4
Classifier: Programming Language :: Python :: 3.5
Classifier: Programming Language :: Python :: 3.6
Requires-Dist: django-model-utils (>=2.0)
